gitzip/__init__.py
gitzip/__main__.py
gitzip/gitzip.py
gitzip/static.py
gitzip/VERSION
gitzip/version.py
gitzip-2.0.1.dist-info/LICENSE
gitzip-2.0.1.dist-info/WHEEL
gitzip-2.0.1.dist-info/METADATA
gitzip-2.0.1.dist-info/RECORD
