Metadata-Version: 2.1
Name: gitzip
Version: 2.0.1
Summary: A small python program to export files changed between git commits or branches to a zip file retaining the directory structure.
Author: miile7
Requires-Python: >=3.8,<4.0
Classifier: Programming Language :: Python :: 3
Classifier: Programming Language :: Python :: 3.8
Classifier: Programming Language :: Python :: 3.9
Classifier: Programming Language :: Python :: 3.10
Classifier: Programming Language :: Python :: 3.11
